certbot_nginx/__init__.py
certbot_nginx/py.typed
certbot_nginx/_internal/__init__.py
certbot_nginx/_internal/configurator.py
certbot_nginx/_internal/constants.py
certbot_nginx/_internal/display_ops.py
certbot_nginx/_internal/http_01.py
certbot_nginx/_internal/nginxparser.py
certbot_nginx/_internal/obj.py
certbot_nginx/_internal/parser.py
certbot_nginx/_internal/parser_obj.py
certbot_nginx/_internal/tests/__init__.py
certbot_nginx/_internal/tests/configurator_test.py
certbot_nginx/_internal/tests/display_ops_test.py
certbot_nginx/_internal/tests/http_01_test.py
certbot_nginx/_internal/tests/nginxparser_test.py
certbot_nginx/_internal/tests/obj_test.py
certbot_nginx/_internal/tests/parser_obj_test.py
certbot_nginx/_internal/tests/parser_test.py
certbot_nginx/_internal/tests/test_util.py
certbot_nginx/_internal/tests/testdata/etc_nginx/broken.conf
certbot_nginx/_internal/tests/testdata/etc_nginx/comment_in_file.conf
certbot_nginx/_internal/tests/testdata/etc_nginx/edge_cases.conf
certbot_nginx/_internal/tests/testdata/etc_nginx/foo.conf
certbot_nginx/_internal/tests/testdata/etc_nginx/invalid_unicode_comments.conf
certbot_nginx/_internal/tests/testdata/etc_nginx/mime.types
certbot_nginx/_internal/tests/testdata/etc_nginx/minimalistic_comments.conf
certbot_nginx/_internal/tests/testdata/etc_nginx/multiline_quotes.conf
certbot_nginx/_internal/tests/testdata/etc_nginx/nginx-include.conf
certbot_nginx/_internal/tests/testdata/etc_nginx/nginx.conf
certbot_nginx/_internal/tests/testdata/etc_nginx/server.conf
certbot_nginx/_internal/tests/testdata/etc_nginx/valid_unicode_comments.conf
certbot_nginx/_internal/tests/testdata/etc_nginx/sites-enabled/addr-80.com
certbot_nginx/_internal/tests/testdata/etc_nginx/sites-enabled/both.com
certbot_nginx/_internal/tests/testdata/etc_nginx/sites-enabled/default
certbot_nginx/_internal/tests/testdata/etc_nginx/sites-enabled/example.com
certbot_nginx/_internal/tests/testdata/etc_nginx/sites-enabled/example.net
certbot_nginx-5.1.0.dist-info/licenses/LICENSE.txt
certbot_nginx-5.1.0.dist-info/METADATA
certbot_nginx-5.1.0.dist-info/WHEEL
certbot_nginx-5.1.0.dist-info/entry_points.txt
certbot_nginx-5.1.0.dist-info/top_level.txt
certbot_nginx-5.1.0.dist-info/RECORD
